openai_page/VERSION
openai_page/__init__.py
openai_page-0.1.1.dist-info/METADATA
openai_page-0.1.1.dist-info/WHEEL
openai_page-0.1.1.dist-info/licenses/LICENSE
openai_page-0.1.1.dist-info/RECORD
