Metadata-Version: 2.4
Name: openai-page
Version: 0.1.1
Summary: OpenAI page base model.
License: MIT
License-File: LICENSE
Author: Allen Chou
Author-email: f1470891079@gmail.com
Requires-Python: >=3.11,<4
Classifier: License :: OSI Approved :: MIT License
Classifier: Programming Language :: Python :: 3
Classifier: Programming Language :: Python :: 3.11
Classifier: Programming Language :: Python :: 3.12
Classifier: Programming Language :: Python :: 3.13
Classifier: Programming Language :: Python :: 3.14
Requires-Dist: pydantic (>=2)
Project-URL: Homepage, https://github.com/allen2c/openai-page
Project-URL: PyPI, https://pypi.org/project/openai-page/
Project-URL: Repository, https://github.com/allen2c/openai-page
